MANIFEST.in
README.rst
setup.cfg
setup.py
./__init__.py
./carrier.py
./configuration.py
./configuration.xml
./country.py
./country.xml
./party.py
./sale.py
./sale.xml
./shipment_bag.py
./shipment_bag.xml
./shipping_data.xml
./stock.py
./stock.xml
./tryton.cfg
./tests/__init__.py
./tests/test_carrier.py
./tests/test_endicia.py
./tests/test_stock.py
./view/endicia_buy_postage_wizard_view_form.xml
./view/endicia_configuration_form.xml
./view/endicia_refund_wizard_view_form.xml
./view/endicia_scanform_wizard_view_form.xml
./view/mailclass_view_form.xml
./view/mailclass_view_tree.xml
./view/sale_configuration_view_form.xml
./view/sale_view_form.xml
./view/shipment_bag_view_form.xml
./view/shipment_bag_view_tree.xml
./view/shipment_view_form.xml
./view/shipping_endicia_configuration_form.xml
trytond_endicia_integration.egg-info/PKG-INFO
trytond_endicia_integration.egg-info/SOURCES.txt
trytond_endicia_integration.egg-info/dependency_links.txt
trytond_endicia_integration.egg-info/entry_points.txt
trytond_endicia_integration.egg-info/not-zip-safe
trytond_endicia_integration.egg-info/requires.txt
trytond_endicia_integration.egg-info/top_level.txt