Metadata-Version: 1.1
Name: trytond-endicia-integration
Version: 3.4.0.1
Summary: Integration with USPS via Endicia for Tryton
Home-page: https://github.com/openlabs/trytond-endicia-integration/
Author: Openlabs Technologies & Consulting (P) Ltd.
Author-email: UNKNOWN
License: GPL-3
Platform: UNKNOWN
Classifier: Development Status :: 4 - Beta
Classifier: Environment :: Plugins
Classifier: Framework :: Tryton
Classifier: Intended Audience :: Developers
Classifier: Intended Audience :: Financial and Insurance Industry
Classifier: Intended Audience :: Legal Industry
Classifier: Intended Audience :: Manufacturing
Classifier: License :: OSI Approved :: GNU General Public License (GPL)
Classifier: Natural Language :: English
Classifier: Operating System :: OS Independent
Classifier: Programming Language :: Python :: 2.6
Classifier: Programming Language :: Python :: 2.7
Classifier: Topic :: Office/Business
